fishclient/__init__.py
fishclient/client.py
fishclient/events.py
fishclient-0.1.4.dist-info/licenses/LICENSE
fishclient-0.1.4.dist-info/METADATA
fishclient-0.1.4.dist-info/WHEEL
fishclient-0.1.4.dist-info/top_level.txt
fishclient-0.1.4.dist-info/RECORD
