Metadata-Version: 2.4
Name: fishclient
Version: 0.1.4
Summary: client for interacting with FishTank.live
Home-page: https://github.com/pluhian/fishclient
Author: pluhian
License-Expression: MIT
Project-URL: Homepage, https://github.com/pluhian/fishclient
Project-URL: Repository, https://github.com/pluhian/fishclient
Requires-Python: >=3.7
License-File: LICENSE
Requires-Dist: requests>=2.25.0
Requires-Dist: websockets>=11.0.3
Requires-Dist: msgpack>=1.0.7
Dynamic: home-page
Dynamic: license-file
Dynamic: requires-python
